drs2/__init__.py
drs2/drsdb.py
drs2-0.0.1.dist-info/LICENSE
drs2-0.0.1.dist-info/METADATA
drs2-0.0.1.dist-info/WHEEL
drs2-0.0.1.dist-info/top_level.txt
drs2-0.0.1.dist-info/RECORD
