Metadata-Version: 2.1
Name: drs2
Version: 0.0.1
Summary: Module for drs2 db calls
License: Apache License
Project-URL: Repository, https://github.com/harvard-lts/drs2-db
Classifier: Programming Language :: Python :: 3
Classifier: License :: OSI Approved :: MIT License
Classifier: Operating System :: OS Independent
Requires-Python: >=3.9
License-File: LICENSE
Requires-Dist: coverage ==7.2.6
Requires-Dist: iniconfig ==2.0.0
Requires-Dist: oracledb ==2.0.0
Requires-Dist: packaging ==23.1
Requires-Dist: pluggy ==1.0.0
Requires-Dist: project-paths ==1.1.1
Requires-Dist: pytest ==7.3.1
Requires-Dist: pytest-mock ==3.10.0
Requires-Dist: python-dotenv ==1.0.0
Requires-Dist: toml ==0.10.2
Requires-Dist: tomli ==2.0.1
